validator/__init__.py
validator/checks.py
validator/main.py
validator/version.py
ugrc_bdc_challenge_validator-1.1.1.dist-info/LICENSE
ugrc_bdc_challenge_validator-1.1.1.dist-info/METADATA
ugrc_bdc_challenge_validator-1.1.1.dist-info/WHEEL
ugrc_bdc_challenge_validator-1.1.1.dist-info/entry_points.txt
ugrc_bdc_challenge_validator-1.1.1.dist-info/top_level.txt
ugrc_bdc_challenge_validator-1.1.1.dist-info/zip-safe
ugrc_bdc_challenge_validator-1.1.1.dist-info/RECORD
