Metadata-Version: 2.1
Name: ugrc-bdc-challenge-validator
Version: 1.1.1
Summary: Project description.
Home-page: https://github.com/agrc/bdc-challenge-validator
Author: UGRC
Author-email: ugrc@utah.gov
License: MIT
Project-URL: Issue Tracker, https://github.com/agrc/python/issues
Keywords: gis
Platform: UNKNOWN
Classifier: Development Status :: 5 - Production/Stable
Classifier: Intended Audience :: Developers
Classifier: Topic :: Utilities
License-File: LICENSE
Requires-Dist: arcgis (>1.7)
Provides-Extra: tests
Requires-Dist: pylint-quotes (~=0.2) ; extra == 'tests'
Requires-Dist: pylint (~=2.11) ; extra == 'tests'
Requires-Dist: pytest-cov (<5,>=3) ; extra == 'tests'
Requires-Dist: pytest-instafail (~=0.4) ; extra == 'tests'
Requires-Dist: pytest-isort (<4,>=2) ; extra == 'tests'
Requires-Dist: pytest-mock (~=3.8) ; extra == 'tests'
Requires-Dist: pytest-pylint (~=0.18) ; extra == 'tests'
Requires-Dist: pytest-watch (~=4.2) ; extra == 'tests'
Requires-Dist: pytest (<8,>=6) ; extra == 'tests'
Requires-Dist: yapf (~=0.31) ; extra == 'tests'
